discombed/__init__.py
discombed-0.0.1.dist-info/LICENSE
discombed-0.0.1.dist-info/METADATA
discombed-0.0.1.dist-info/WHEEL
discombed-0.0.1.dist-info/top_level.txt
discombed-0.0.1.dist-info/RECORD
