Metadata-Version: 2.1
Name: discombed
Version: 0.0.1
Summary: A bad discord webhooks wrapper
Home-page: https://github.com/darkdragon532/discombed
Author: DARKDRAGON532
License: UNKNOWN
Platform: UNKNOWN
Classifier: Programming Language :: Python :: 3
Classifier: License :: OSI Approved :: GNU General Public License v3 (GPLv3)
Classifier: Operating System :: OS Independent
Requires-Python: >=3.6
Requires-Dist: requests
